[
  {
    "resourceType": "Questionnaire",
    "id": "e39648cc-1180-4e82-b269-2074852750b9",
    "status": "active",
    "title": "Patient Intake Form",
    "description": "Comprehensive patient intake questionnaire for new admissions",
    "subjectType": [
      "Patient"
    ],
    "item": [
      {
        "linkId": "1",
        "text": "Personal Information",
        "type": "group",
        "item": [
          {
            "linkId": "1.1",
            "text": "Date of Birth",
            "type": "date",
            "required": true
          },
          {
            "linkId": "1.2",
            "text": "Gender",
            "type": "choice",
            "required": true,
            "answerOption": [
              {
                "valueCoding": {
                  "code": "male",
                  "display": "Male"
                }
              },
              {
                "valueCoding": {
                  "code": "female",
                  "display": "Female"
                }
              }
            ]
          },
          {
            "linkId": "1.3",
            "text": "Emergency Contact Name",
            "type": "string",
            "required": true
          },
          {
            "linkId": "1.4",
            "text": "Emergency Contact Phone",
            "type": "string",
            "required": true
          }
        ]
      },
      {
        "linkId": "2",
        "text": "Medical History",
        "type": "group",
        "item": [
          {
            "linkId": "2.1",
            "text": "Do you have any known allergies?",
            "type": "boolean",
            "required": false
          },
          {
            "linkId": "2.2",
            "text": "Current Medications",
            "type": "text",
            "required": false
          },
          {
            "linkId": "2.3",
            "text": "Past Surgeries",
            "type": "text",
            "required": false
          },
          {
            "linkId": "2.4",
            "text": "Family Medical History",
            "type": "text",
            "required": false
          }
        ]
      }
    ]
  },
  {
    "resourceType": "Questionnaire",
    "id": "0372fd0d-8088-4149-8cf6-c801082d836b",
    "status": "active",
    "title": "Pre-Surgery Assessment",
    "description": "Pre-operative assessment questionnaire",
    "subjectType": [
      "Patient"
    ],
    "item": [
      {
        "linkId": "1",
        "text": "Surgery Information",
        "type": "group",
        "item": [
          {
            "linkId": "1.1",
            "text": "Type of Surgery",
            "type": "string",
            "required": true
          },
          {
            "linkId": "1.2",
            "text": "Previous Surgeries",
            "type": "text",
            "required": false
          },
          {
            "linkId": "1.3",
            "text": "Current Medications",
            "type": "text",
            "required": true
          },
          {
            "linkId": "1.4",
            "text": "Allergies to Medications",
            "type": "text",
            "required": false
          }
        ]
      },
      {
        "linkId": "2",
        "text": "Health Status",
        "type": "group",
        "item": [
          {
            "linkId": "2.1",
            "text": "Do you smoke?",
            "type": "boolean",
            "required": false
          },
          {
            "linkId": "2.2",
            "text": "Do you consume alcohol?",
            "type": "boolean",
            "required": false
          },
          {
            "linkId": "2.3",
            "text": "Any bleeding disorders?",
            "type": "boolean",
            "required": false
          }
        ]
      }
    ]
  },
  {
    "resourceType": "Questionnaire",
    "id": "f738f0e5-1b79-4df0-9a4a-713c97d0eb31",
    "status": "active",
    "title": "Post-Visit Feedback",
    "description": "Patient feedback questionnaire after hospital visit",
    "subjectType": [
      "Patient"
    ],
    "item": [
      {
        "linkId": "1",
        "text": "Visit Experience",
        "type": "group",
        "item": [
          {
            "linkId": "1.1",
            "text": "How would you rate your overall experience?",
            "type": "choice",
            "required": true,
            "answerOption": [
              {
                "valueCoding": {
                  "code": "excellent",
                  "display": "Excellent"
                }
              },
              {
                "valueCoding": {
                  "code": "good",
                  "display": "Good"
                }
              },
              {
                "valueCoding": {
                  "code": "fair",
                  "display": "Fair"
                }
              },
              {
                "valueCoding": {
                  "code": "poor",
                  "display": "Poor"
                }
              }
            ]
          },
          {
            "linkId": "1.2",
            "text": "Were your questions answered?",
            "type": "boolean",
            "required": false
          },
          {
            "linkId": "1.3",
            "text": "Would you recommend this hospital?",
            "type": "boolean",
            "required": false
          },
          {
            "linkId": "1.4",
            "text": "Additional Comments",
            "type": "text",
            "required": false
          }
        ]
      }
    ]
  }
]